connectorlocal/__init__.py
connectorlocal/connectorlocal.py
connectorlocal-0.1.2.dist-info/LICENSE
connectorlocal-0.1.2.dist-info/METADATA
connectorlocal-0.1.2.dist-info/WHEEL
connectorlocal-0.1.2.dist-info/top_level.txt
connectorlocal-0.1.2.dist-info/RECORD
